tinybench/__init__.py
tinybench/tinybench.py
tinybench/tmp.py
tinybench/tests/__init__.py
tinybench/tests/test.py
tinybench-1.0.2.dist-info/LICENSE
tinybench-1.0.2.dist-info/METADATA
tinybench-1.0.2.dist-info/WHEEL
tinybench-1.0.2.dist-info/top_level.txt
tinybench-1.0.2.dist-info/RECORD
