Metadata-Version: 2.1
Name: tinybench
Version: 1.0.2
Summary: A microbenchmark for Python
Home-page: https://github.com/AD-Ventures/tinybench
Author: AD Ventures
Author-email: abir.dahlin.ventures@gmail.com
License: UNKNOWN
Platform: UNKNOWN
Classifier: Programming Language :: Python :: 3
Classifier: License :: OSI Approved :: MIT License
Classifier: Operating System :: OS Independent
Requires-Python: >=3.3
Requires-Dist: matplotlib
